{
    "move up"                 : "up",
    "move down"               : "down",
    "move left"               : "left",
    "move right"              : "right",
    "scroll up"               : "w",
    "scroll down"             : "s",
    "scroll left"             : "a",
    "scroll right"            : "d",
    "left click"              : "z",
    "middle click"            : "x",
    "right click"             : "c",
    "toggle combo 1st button" : "print screen",
    "toggle combo 2nd button" : "insert",
    "cursor speed 1"          : "1",
    "cursor speed 2"          : "2",
    "cursor speed 3"          : "3",
    "cursor speed 4"          : "4",
    "cursor speed 5"          : "5",
    "cursor speed 6"          : "6",
    "cursor speed 7"          : "7",
    "cursor speed 8"          : "8",
    "cursor speed 9"          : "9",
    "cursor speed 10"         : "0",
    "exit"                    : "esc"
}